ocr/DetectChars.py
ocr/DetectPlates.py
ocr/Main.py
ocr/PossibleChar.py
ocr/PossiblePlate.py
ocr/Preprocess.py
ocrzzz-1.0.0.dist-info/LICENSE
ocrzzz-1.0.0.dist-info/METADATA
ocrzzz-1.0.0.dist-info/WHEEL
ocrzzz-1.0.0.dist-info/entry_points.txt
ocrzzz-1.0.0.dist-info/top_level.txt
ocrzzz-1.0.0.dist-info/RECORD
